{"name":"build-javascript","namedChunkGroups":{"polyfill":{"name":"polyfill","assets":[{"name":"webpack-runtime-9274c1ae9dbd2e0ee58f.js","size":3249},{"name":"polyfill-83874da4d59ffe6f8ac1.js","size":85021}],"filteredAssets":0,"assetsSize":88270,"filteredAuxiliaryAssets":2,"auxiliaryAssetsSize":224177},"app":{"name":"app","assets":[{"name":"webpack-runtime-9274c1ae9dbd2e0ee58f.js","size":3249},{"name":"framework-de643ed28ebff9625fc6.js","size":140548},{"name":"styles.ac31356ce9b5cfa32c78.css","size":4130},{"name":"app-a7fa03438a64245f526e.js","size":78370}],"filteredAssets":0,"assetsSize":226297,"filteredAuxiliaryAssets":3,"auxiliaryAssetsSize":701238},"component---src-pages-404-tsx":{"name":"component---src-pages-404-tsx","assets":[{"name":"component---src-pages-404-tsx-3a4bbffe8a0e7c8d3905.js","size":792}],"filteredAssets":0,"assetsSize":792,"filteredAuxiliaryAssets":1,"auxiliaryAssetsSize":2010},"component---src-pages-index-tsx":{"name":"component---src-pages-index-tsx","assets":[{"name":"component---src-pages-index-tsx-ce5d64b70a934fa98d3f.js","size":4219}],"filteredAssets":0,"assetsSize":4219,"filteredAuxiliaryAssets":1,"auxiliaryAssetsSize":8836}},"assetsByChunkName":{"polyfill":["webpack-runtime-9274c1ae9dbd2e0ee58f.js","polyfill-83874da4d59ffe6f8ac1.js"],"app":["webpack-runtime-9274c1ae9dbd2e0ee58f.js","framework-de643ed28ebff9625fc6.js","styles.ac31356ce9b5cfa32c78.css","app-a7fa03438a64245f526e.js"],"component---src-pages-404-tsx":["component---src-pages-404-tsx-3a4bbffe8a0e7c8d3905.js"],"component---src-pages-index-tsx":["component---src-pages-index-tsx-ce5d64b70a934fa98d3f.js"]},"childAssetsByChunkName":{}}